ds_tools/__init__.py
ds_tools/ds_tools.py
ds_tools-0.1.3.dist-info/METADATA
ds_tools-0.1.3.dist-info/WHEEL
ds_tools-0.1.3.dist-info/top_level.txt
ds_tools-0.1.3.dist-info/RECORD
