Metadata-Version: 2.1
Name: ds-tools
Version: 0.1.3
Summary: Data science useful toolkit
Home-page: https://github.com/jielu0728/ds_tools
Author: Jie Lu
Author-email: jielu0728@gmail.com
License: UNKNOWN
Platform: UNKNOWN
Classifier: Programming Language :: Python :: 3
Classifier: License :: OSI Approved :: MIT License
Classifier: Operating System :: OS Independent
